LICENSE
MANIFEST.in
Makefile
README
setup.py
data/po/LINGUAS
data/po/Makefile
data/po/POTFILES.in
data/po/README
data/po/summary.py
data/po/validate.sh
src/sleipnir/__init__.py
src/sleipnir.shell.egg-info/PKG-INFO
src/sleipnir.shell.egg-info/SOURCES.txt
src/sleipnir.shell.egg-info/dependency_links.txt
src/sleipnir.shell.egg-info/entry_points.txt
src/sleipnir.shell.egg-info/namespace_packages.txt
src/sleipnir.shell.egg-info/not-zip-safe
src/sleipnir.shell.egg-info/requires.txt
src/sleipnir.shell.egg-info/top_level.txt
src/sleipnir/shell/__init__.py
src/sleipnir/shell/application.py
src/sleipnir/shell/arguments.py
src/sleipnir/shell/constants.py
src/sleipnir/shell/formatters.py
src/sleipnir/shell/hooks.py
src/sleipnir/shell/platform.py
src/sleipnir/shell/runner.py
src/sleipnir/shell/shell.py
src/sleipnir/shell/interfaces/__init__.py
src/sleipnir/shell/interfaces/application.py
tests/__init__.py
tests/integration/__init__.py