Metadata-Version: 1.1
Name: sleipnir.shell
Version: 0.2.2
Summary: A logistic system
Home-page: http://sleipnir.liberalia.net/
Author: Carlos Martín
Author-email: cmartin@liberalia.net
License: GNU General Public License, version 2
Platform: UNKNOWN
Classifier: Development Status :: 4 - Beta
Classifier: License :: OSI Approved :: GNU General Public License (GPL)
Classifier: Environment :: Handhelds/PDA's
Classifier: Intended Audience :: Customer Service
Classifier: Operating System :: POSIX :: Linux
Classifier: Programming Language :: Python :: 2.6
Classifier: Programming Language :: Python :: 2.7
Classifier: Topic :: Office/Business :: Scheduling
